Metadata-Version: 2.1
Name: sentry-dingtalk-henryhaoson2
Version: 9.0.3
Summary: A sentry extension integrates DingTalk robot webhook forked from Jedore/sentry-dingtalk
Home-page: https://git.17bdc.com/android-apps/sentry-dingtalk
Author: Henryhaoson
Author-email: hao.zhu@shanbay.com
License: MIT
Keywords: sentry dingtalk
Classifier: License :: OSI Approved :: MIT License
Classifier: Programming Language :: Python
Classifier: Programming Language :: Python :: 3
Classifier: Programming Language :: Python :: 3.6
Classifier: Programming Language :: Python :: 3.7
Classifier: Programming Language :: Python :: Implementation :: CPython
Requires-Python: >=3.6.13
License-File: LICENSE
Requires-Dist: sentry >=21.5.1
